llama_index/agent/openai/__init__.py
llama_index/agent/openai/base.py
llama_index/agent/openai/openai_assistant_agent.py
llama_index/agent/openai/step.py
llama_index/agent/openai/utils.py
llama_index_agent_openai-0.2.1.dist-info/METADATA
llama_index_agent_openai-0.2.1.dist-info/WHEEL
llama_index_agent_openai-0.2.1.dist-info/RECORD
